protosync/__init__.py
protosync/main.py
protosync/common/__init__.py
protosync/common/common.py
protosync/dest/__init__.py
protosync/dest/dest.py
protosync/source/__init__.py
protosync/source/source.py
protosync-0.0.4.9.dist-info/METADATA
protosync-0.0.4.9.dist-info/WHEEL
protosync-0.0.4.9.dist-info/entry_points.txt
protosync-0.0.4.9.dist-info/top_level.txt
protosync-0.0.4.9.dist-info/RECORD
