Metadata-Version: 2.1
Name: protosync
Version: 0.0.4.9
Summary: Sync code with a remote server in real time
Home-page: https://github.com/yl573/protosync
Author: Edward Liu
Author-email: edwardliu573@gmail.com
License: UNKNOWN
Platform: UNKNOWN
Classifier: Programming Language :: Python :: 3
Classifier: License :: OSI Approved :: MIT License
Classifier: Operating System :: OS Independent
Requires-Dist: dill (==0.2.7.1)
Requires-Dist: pyrsync2 (==0.2.6)
Requires-Dist: requests (==2.20.0)
Requires-Dist: cryptography (==2.4.2)
Requires-Dist: gitignore-parser (==0.0.3)
Requires-Dist: attrdict (==2.0.0)
